ci/integration/repo/devenv/sync.py
devenv/__init__.py
devenv/__main__.py
devenv/bootstrap.py
devenv/colima.py
devenv/constants.py
devenv/doctor.py
devenv/fetch.py
devenv/main.py
devenv/pin_gha.py
devenv/py.typed
devenv/pythons.py
devenv/sync.py
devenv/update.py
devenv/checks/__init__.py
devenv/checks/colimaSsh.py
devenv/checks/dockerConfig.py
devenv/checks/dockerDesktop.py
devenv/checks/limaDns.py
devenv/checks/test.py
devenv/lib/__init__.py
devenv/lib/archive.py
devenv/lib/brew.py
devenv/lib/colima.py
devenv/lib/config.py
devenv/lib/context.py
devenv/lib/direnv.py
devenv/lib/docker.py
devenv/lib/fs.py
devenv/lib/gcloud.py
devenv/lib/github.py
devenv/lib/limactl.py
devenv/lib/modules.py
devenv/lib/node.py
devenv/lib/proc.py
devenv/lib/repository.py
devenv/lib/rosetta.py
devenv/lib/tenv.py
devenv/lib/uv.py
devenv/lib/venv.py
devenv/lib_check/__init__.py
devenv/lib_check/brew.py
devenv/lib_check/types.py
tests/__init__.py
tests/conftest.py
tests/test_main.py
tests/test_pythons.py
tests/test_sync.py
tests/utils.py
tests/checks/__init__.py
tests/checks/test_dockerConfig.py
tests/doctor/__init__.py
tests/doctor/test_attempt_fix.py
tests/doctor/test_filter_failing_checks.py
tests/doctor/test_load_checks.py
tests/doctor/test_prompt_for_fix.py
tests/doctor/test_run_checks.py
tests/doctor/devenv/checks/bad_check.py
tests/doctor/devenv/checks/bad_fix.py
tests/doctor/devenv/checks/broken_check.py
tests/doctor/devenv/checks/broken_fix.py
tests/doctor/devenv/checks/failing_check.py
tests/doctor/devenv/checks/failing_check_with_msg.py
tests/doctor/devenv/checks/no_check.py
tests/doctor/devenv/checks/no_name.py
tests/doctor/devenv/checks/no_tags.py
tests/doctor/devenv/checks/passing_check.py
tests/lib/test_archive.py
tests/lib/test_brew.py
tests/lib/test_direnv.py
tests/lib/test_fs.py
tests/lib/test_github.py
tests/lib/test_node.py
tests/lib/test_proc.py
tests/lib/test_repository.py
tests/lib/test_venv.py
sentry_devenv-1.25.0.dist-info/METADATA
sentry_devenv-1.25.0.dist-info/WHEEL
sentry_devenv-1.25.0.dist-info/entry_points.txt
sentry_devenv-1.25.0.dist-info/top_level.txt
sentry_devenv-1.25.0.dist-info/RECORD
