Metadata-Version: 2.4
Name: sentry_devenv
Version: 1.25.0
Summary: Utilities for setting up a Sentry development environment
Author-email: Joshua Li <joshua.li@sentry.io>, Ian Woodard <ian.woodard@sentry.io>, Buck Evan <buck.evan@sentry.io>
Classifier: Programming Language :: Python :: 3
Classifier: License :: OSI Approved :: Apache Software License
Classifier: Operating System :: OS Independent
Requires-Python: >=3.10
Requires-Dist: typing_extensions
Requires-Dist: sentry-sdk
